__init__.py
__main__.py
markdown_quote.py
markdown_quote-0.0.2.dist-info/licenses/LICENSE
markdown_quote-0.0.2.dist-info/METADATA
markdown_quote-0.0.2.dist-info/WHEEL
markdown_quote-0.0.2.dist-info/entry_points.txt
markdown_quote-0.0.2.dist-info/top_level.txt
markdown_quote-0.0.2.dist-info/RECORD
