Metadata-Version: 2.4
Name: markdown_quote
Version: 0.0.2
Summary: A command line tool that processes markdown files to replace quote blocks with actual content from referenced files.
Author-email: ybbh <guohua@scupt.com>
License: Apache License
Project-URL: Homepage, https://github.com/scuptio/markdown_quote
Project-URL: Repository, https://github.com/scuptio/markdown_quote
Project-URL: Bug Reports, https://github.com/scuptio/markdown_quote/issues
Keywords: cli,command-line
Classifier: Programming Language :: Python :: 3
Classifier: Programming Language :: Python :: 3.7
Classifier: Programming Language :: Python :: 3.8
Classifier: Programming Language :: Python :: 3.9
Classifier: Programming Language :: Python :: 3.10
Classifier: Programming Language :: Python :: 3.11
License-File: LICENSE
Dynamic: license-file
